epew.py
epew-3.4.7.dist-info/METADATA
epew-3.4.7.dist-info/WHEEL
epew-3.4.7.dist-info/entry_points.txt
epew-3.4.7.dist-info/top_level.txt
epew-3.4.7.dist-info/RECORD
