Metadata-Version: 2.1
Name: epew
Version: 3.4.7
Summary: epew (ExternalProgramExecutionWrapper) is a tool to wrap program-calls with some useful functions like getting stdout, stderr, exitcode and the ability to set a timeout.
Home-page: https://github.com/anionDev/ExternalProgramExecutionWrapper
Author: Marius Göcke
Author-email: marius.goecke@gmail.com
License: MIT
Platform: windows10
Platform: linux
Classifier: Programming Language :: Python :: 3.8
Classifier: License :: OSI Approved :: MIT License
Classifier: Operating System :: POSIX :: Linux
Classifier: Operating System :: Microsoft :: Windows :: Windows 10
Classifier: Topic :: System :: Logging
Classifier: Topic :: System :: Monitoring
Classifier: Topic :: Terminals
